FleekAPI/__init__.py
FleekAPI/app.py
FleekAPI/middleware.py
FleekAPI/response.py
fleekapi/__init__.py
fleekapi/app.py
fleekapi/middleware.py
fleekapi/response.py
fleekapi/src/__init__.py
fleekapi/src/app.py
fleekapi/src/middleware.py
fleekapi/src/response.py
fleekapi-0.2.6.dist-info/METADATA
fleekapi-0.2.6.dist-info/WHEEL
fleekapi-0.2.6.dist-info/top_level.txt
fleekapi-0.2.6.dist-info/RECORD
