Metadata-Version: 2.1
Name: fleekapi
Version: 0.2.6
Summary: My short description for my project.
Home-page: https://github.com/under-script/fleekapi
Author: Yunusov Abdulmajid
Author-email: abdulmajidyunusov18@gmail.com
License: MIT
Classifier: License :: OSI Approved :: MIT License
Classifier: Programming Language :: Python
Classifier: Programming Language :: Python :: 3
Classifier: Programming Language :: Python :: 3.6
Classifier: Programming Language :: Python :: Implementation :: CPython
Classifier: Programming Language :: Python :: Implementation :: PyPy
Requires-Python: >=3.9.0
Requires-Dist: gunicorn ==22.0.0
Requires-Dist: Jinja2 ==3.1.4
Requires-Dist: parse ==1.20.1
Requires-Dist: requests ==2.31.0
Requires-Dist: requests-wsgi-adapter ==0.4.1
Requires-Dist: WebOb ==1.8.7
Requires-Dist: whitenoise ==6.6.0
Requires-Dist: icecream ==2.1.3
Requires-Dist: Werkzeug ==3.0.3
